cs/progress.py
cs_progress-20250530.dist-info/WHEEL
cs_progress-20250530.dist-info/METADATA
cs_progress-20250530.dist-info/RECORD
