Metadata-Version: 2.4
Name: cs-progress
Version: 20250530
Summary: A progress tracker with methods for throughput, ETA and update notification; also a compound progress meter composed from other progress meters.
Keywords: python2,python3
Author-email: Cameron Simpson <cs@cskk.id.au>
Classifier: Programming Language :: Python
Classifier: Programming Language :: Python :: 3
Classifier: Development Status :: 4 - Beta
Classifier: Intended Audience :: Developers
Classifier: Operating System :: OS Independent
Classifier: Topic :: Software Development :: Libraries :: Python Modules
Classifier: License :: OSI Approved :: GNU General Public License v3 or later (GPLv3+)
Requires-Dist: cs.deco>=20250513
Requires-Dist: cs.logutils>=20250323
Requires-Dist: cs.py.func>=20240630
Requires-Dist: cs.queues>=20250426
Requires-Dist: cs.resources>=20250325
Requires-Dist: cs.seq>=20250306
Requires-Dist: cs.units>=20250528
Requires-Dist: cs.upd>=20250426
Requires-Dist: icontract
Requires-Dist: typeguard
Project-URL: MonoRepo Commits, https://bitbucket.org/cameron_simpson/css/commits/branch/main
Project-URL: Monorepo Git Mirror, https://github.com/cameron-simpson/css
Project-URL: Monorepo Hg/Mercurial Mirror, https://hg.sr.ht/~cameron-simpson/css
Project-URL: Source, https://github.com/cameron-simpson/css/blob/main/lib/python/cs/progress.py
